{
 "served": 143,
 "total": 444,
 "topic_tot": {
  "thanks_closing": 53,
  "greeting": 38,
  "purchase_intent": 11,
  "product_question": 22,
  "complaint_problem": 36,
  "other": 38,
  "exchange_return": 79,
  "payment_discount": 7,
  "shipping_coordination": 64,
  "order_status": 69,
  "restock_availability": 25,
  "wholesale_b2b": 2
 },
 "topic_served": {
  "thanks_closing": 43,
  "greeting": 36,
  "purchase_intent": 3,
  "product_question": 3,
  "other": 11,
  "exchange_return": 9,
  "shipping_coordination": 11,
  "order_status": 20,
  "restock_availability": 2,
  "complaint_problem": 4,
  "payment_discount": 1,
  "wholesale_b2b": 0
 }
}